autoai_libs/__init__.py
autoai_libs/version.cp312-win_amd64.pyd
autoai_libs/version.py
autoai_libs/cognito/__init__.py
autoai_libs/cognito/transforms/__init__.py
autoai_libs/cognito/transforms/sklearn_compat.cp312-win_amd64.pyd
autoai_libs/cognito/transforms/sklearn_compat.py
autoai_libs/cognito/transforms/textras_methods.cp312-win_amd64.pyd
autoai_libs/cognito/transforms/textras_methods.py
autoai_libs/cognito/transforms/transform_extras.cp312-win_amd64.pyd
autoai_libs/cognito/transforms/transform_extras.py
autoai_libs/cognito/transforms/transform_utils.cp312-win_amd64.pyd
autoai_libs/cognito/transforms/transform_utils.py
autoai_libs/detectors/__init__.py
autoai_libs/detectors/general_detector.cp312-win_amd64.pyd
autoai_libs/detectors/general_detector.py
autoai_libs/detectors/small_data_detector.cp312-win_amd64.pyd
autoai_libs/detectors/small_data_detector.py
autoai_libs/detectors/date_time/__init__.py
autoai_libs/detectors/date_time/date_time_detector.cp312-win_amd64.pyd
autoai_libs/detectors/date_time/date_time_detector.py
autoai_libs/estimators/__init__.py
autoai_libs/estimators/xgboost.cp312-win_amd64.pyd
autoai_libs/estimators/xgboost.py
autoai_libs/lale/__init__.py
autoai_libs/lale/_common_schemas.cp312-win_amd64.pyd
autoai_libs/lale/_common_schemas.py
autoai_libs/lale/boolean2float.cp312-win_amd64.pyd
autoai_libs/lale/boolean2float.py
autoai_libs/lale/cat_encoder.cp312-win_amd64.pyd
autoai_libs/lale/cat_encoder.py
autoai_libs/lale/cat_imputer.cp312-win_amd64.pyd
autoai_libs/lale/cat_imputer.py
autoai_libs/lale/column_selector.cp312-win_amd64.pyd
autoai_libs/lale/column_selector.py
autoai_libs/lale/compress_strings.cp312-win_amd64.pyd
autoai_libs/lale/compress_strings.py
autoai_libs/lale/date_transformer.cp312-win_amd64.pyd
autoai_libs/lale/date_transformer.py
autoai_libs/lale/float32_transform.cp312-win_amd64.pyd
autoai_libs/lale/float32_transform.py
autoai_libs/lale/float_str2_float.cp312-win_amd64.pyd
autoai_libs/lale/float_str2_float.py
autoai_libs-3.0.10.dist-info/licenses/licenses/LA_cs
autoai_libs-3.0.10.dist-info/licenses/licenses/LA_de
autoai_libs-3.0.10.dist-info/licenses/licenses/LA_el
autoai_libs-3.0.10.dist-info/licenses/licenses/LA_en
autoai_libs-3.0.10.dist-info/licenses/licenses/LA_es
autoai_libs-3.0.10.dist-info/licenses/licenses/LA_fr
autoai_libs-3.0.10.dist-info/licenses/licenses/LA_in
autoai_libs-3.0.10.dist-info/licenses/licenses/LA_it
autoai_libs-3.0.10.dist-info/licenses/licenses/LA_ja
autoai_libs-3.0.10.dist-info/licenses/licenses/LA_ko
autoai_libs-3.0.10.dist-info/licenses/licenses/LA_lt
autoai_libs-3.0.10.dist-info/licenses/licenses/LA_pl
autoai_libs-3.0.10.dist-info/licenses/licenses/LA_pt
autoai_libs-3.0.10.dist-info/licenses/licenses/LA_ru
autoai_libs-3.0.10.dist-info/licenses/licenses/LA_sl
autoai_libs-3.0.10.dist-info/licenses/licenses/LA_tr
autoai_libs-3.0.10.dist-info/licenses/licenses/LA_zh
autoai_libs-3.0.10.dist-info/licenses/licenses/LA_zh_TW
autoai_libs-3.0.10.dist-info/licenses/licenses/LI_cs
autoai_libs-3.0.10.dist-info/licenses/licenses/LI_de
autoai_libs-3.0.10.dist-info/licenses/licenses/LI_el
autoai_libs-3.0.10.dist-info/licenses/licenses/LI_en
autoai_libs-3.0.10.dist-info/licenses/licenses/LI_es
autoai_libs-3.0.10.dist-info/licenses/licenses/LI_fr
autoai_libs-3.0.10.dist-info/licenses/licenses/LI_in
autoai_libs-3.0.10.dist-info/licenses/licenses/LI_it
autoai_libs-3.0.10.dist-info/licenses/licenses/LI_ja
autoai_libs-3.0.10.dist-info/licenses/licenses/LI_ko
autoai_libs-3.0.10.dist-info/licenses/licenses/LI_lt
autoai_libs-3.0.10.dist-info/licenses/licenses/LI_pl
autoai_libs-3.0.10.dist-info/licenses/licenses/LI_pt
autoai_libs-3.0.10.dist-info/licenses/licenses/LI_ru
autoai_libs-3.0.10.dist-info/licenses/licenses/LI_sl
autoai_libs-3.0.10.dist-info/licenses/licenses/LI_tr
autoai_libs-3.0.10.dist-info/licenses/licenses/LI_zh
autoai_libs-3.0.10.dist-info/licenses/licenses/LI_zh_TW
autoai_libs-3.0.10.dist-info/METADATA
autoai_libs-3.0.10.dist-info/WHEEL
autoai_libs-3.0.10.dist-info/top_level.txt
autoai_libs-3.0.10.dist-info/RECORD
