Metadata-Version: 2.4
Name: autoai_libs
Version: 3.0.10
Summary: A library of transformers to support portable representations of AutoAI pipelines
Author: IBM
Author-email: Lukasz Cmielowski <lukasz.cmielowski@pl.ibm.com>, Daniel Ryszka <daniel.ryszka@pl.ibm.com>
Maintainer-email: Łukasz Ćmielowski <lukasz.cmielowski@pl.ibm.com>, Marta Tomzik <marta.tomzik@ibm.com>
License: See: https://www14.software.ibm.com/cgi-bin/weblap/lap.pl?li_formnum=L-AMCU-BYY6S5
Project-URL: homepage, https://dataplatform.cloud.ibm.com/docs/content/wsj/analyze-data/autoai-lib-python.html
Keywords: AI,Watson,IBM,AutoAI,SDK,API,IBM Cloud,Machine Learning
Classifier: Development Status :: 5 - Production/Stable
Classifier: Natural Language :: English
Classifier: Programming Language :: Python :: 3.12
Classifier: Operating System :: MacOS :: MacOS X
Classifier: Operating System :: Microsoft :: Windows
Classifier: Operating System :: POSIX :: Linux
Classifier: Intended Audience :: Science/Research
Classifier: Intended Audience :: Developers
Classifier: Intended Audience :: Information Technology
Classifier: License :: Other/Proprietary License
Classifier: Topic :: Software Development :: Libraries
Classifier: Topic :: Software Development :: Libraries :: Python Modules
Classifier: Topic :: Scientific/Engineering :: Artificial Intelligence
Requires-Python: ~=3.12.0
License-File: licenses/LA_cs
License-File: licenses/LA_de
License-File: licenses/LA_el
License-File: licenses/LA_en
License-File: licenses/LA_es
License-File: licenses/LA_fr
License-File: licenses/LA_in
License-File: licenses/LA_it
License-File: licenses/LA_ja
License-File: licenses/LA_ko
License-File: licenses/LA_lt
License-File: licenses/LA_pl
License-File: licenses/LA_pt
License-File: licenses/LA_ru
License-File: licenses/LA_sl
License-File: licenses/LA_tr
License-File: licenses/LA_zh
License-File: licenses/LA_zh_TW
License-File: licenses/LI_cs
License-File: licenses/LI_de
License-File: licenses/LI_el
License-File: licenses/LI_en
License-File: licenses/LI_es
License-File: licenses/LI_fr
License-File: licenses/LI_in
License-File: licenses/LI_it
License-File: licenses/LI_ja
License-File: licenses/LI_ko
License-File: licenses/LI_lt
License-File: licenses/LI_pl
License-File: licenses/LI_pt
License-File: licenses/LI_ru
License-File: licenses/LI_sl
License-File: licenses/LI_tr
License-File: licenses/LI_zh
License-File: licenses/LI_zh_TW
Requires-Dist: numpy<2.1,>=2.0.2
Requires-Dist: lale<0.10,>=0.9.0
Requires-Dist: attrs<=25.3.0
Requires-Dist: pandas<2.3,>=2.2.3
Requires-Dist: parameterized<0.10,>=0.9
Requires-Dist: scikit-learn<1.7,>=1.6.1
Requires-Dist: xgboost<2.2,>=2.1.3
Requires-Dist: protobuf>=4.21.12
Requires-Dist: packaging
Provides-Extra: test
Requires-Dist: pytest<8.0.0; extra == "test"
Provides-Extra: code-check
Requires-Dist: black; extra == "code-check"
Requires-Dist: isort; extra == "code-check"
Provides-Extra: dev
Requires-Dist: autoai_libs[test]; extra == "dev"
Requires-Dist: autoai_libs[code-check]; extra == "dev"
Provides-Extra: onnx
Requires-Dist: onnx==1.17; extra == "onnx"
Requires-Dist: skl2onnx==1.18.0; extra == "onnx"
Requires-Dist: onnxruntime-extensions==0.13.0; (platform_machine != "ppc64le" and platform_machine != "s390x") and extra == "onnx"
Requires-Dist: lightgbm<4.7,>=4.6; extra == "onnx"
Requires-Dist: onnxmltools==1.14.0; extra == "onnx"
Requires-Dist: onnxconverter-common<=1.14.0; extra == "onnx"
Requires-Dist: snapml<1.17,>=1.16; extra == "onnx"
Provides-Extra: onnx-dev
Requires-Dist: autoai_libs[dev]; extra == "onnx-dev"
Requires-Dist: autoai_libs[onnx]; extra == "onnx-dev"
Requires-Dist: onnxruntime==1.21.0; (platform_machine != "ppc64le" and platform_machine != "s390x") and extra == "onnx-dev"
Dynamic: license-file
